ncm/__init__.py
ncm/api.py
ncm/cli.py
ncm/config.py
ncm/constants.py
ncm/downloader.py
ncm/encrypt.py
ncm/file_util.py
netease_cloud_music_dl_tddschn-0.3.1.dist-info/entry_points.txt
netease_cloud_music_dl_tddschn-0.3.1.dist-info/LICENSE.txt
netease_cloud_music_dl_tddschn-0.3.1.dist-info/WHEEL
netease_cloud_music_dl_tddschn-0.3.1.dist-info/METADATA
netease_cloud_music_dl_tddschn-0.3.1.dist-info/RECORD
