Metadata-Version: 2.1
Name: netease-cloud-music-dl-tddschn
Version: 0.3.1
Summary: Netease cloud music song downloader, with full ID3 metadata!
Home-page: https://github.com/tddschn/netease-cloud-music-dl
License: MIT
Keywords: netease-music,netease-cloud-music,ncm,music,downloader,cli
Author: codezjx
Author-email: code.zjx@gmail.com
Requires-Python: >=3.10,<4.0
Classifier: License :: OSI Approved :: MIT License
Classifier: Programming Language :: Python :: 3
Classifier: Programming Language :: Python :: 3.10
Classifier: Topic :: Utilities
Requires-Dist: Pillow (>=4.3.0)
Requires-Dist: mutagen (>=1.38.0)
Requires-Dist: pycryptodomex (>=3.16.0,<4.0.0)
Requires-Dist: requests (>=2.17.3)
Project-URL: Bug Tracker, https://github.com/tddschn/netease-cloud-music-dl/issues
Project-URL: Repository, https://github.com/tddschn/netease-cloud-music-dl
